commands2/__init__.py
commands2/cmd.py
commands2/command.py
commands2/commandscheduler.py
commands2/conditionalcommand.py
commands2/deferredcommand.py
commands2/exceptions.py
commands2/functionalcommand.py
commands2/instantcommand.py
commands2/notifiercommand.py
commands2/parallelcommandgroup.py
commands2/paralleldeadlinegroup.py
commands2/parallelracegroup.py
commands2/pidcommand.py
commands2/pidsubsystem.py
commands2/printcommand.py
commands2/profiledpidcommand.py
commands2/profiledpidsubsystem.py
commands2/proxycommand.py
commands2/py.typed
commands2/repeatcommand.py
commands2/runcommand.py
commands2/schedulecommand.py
commands2/selectcommand.py
commands2/sequentialcommandgroup.py
commands2/startendcommand.py
commands2/subsystem.py
commands2/swervecontrollercommand.py
commands2/timedcommandrobot.py
commands2/trapezoidprofilecommand.py
commands2/trapezoidprofilesubsystem.py
commands2/typing.py
commands2/util.py
commands2/waitcommand.py
commands2/waituntilcommand.py
commands2/wrappercommand.py
commands2/button/__init__.py
commands2/button/commandgenerichid.py
commands2/button/commandjoystick.py
commands2/button/commandps4controller.py
commands2/button/commandxboxcontroller.py
commands2/button/joystickbutton.py
commands2/button/networkbutton.py
commands2/button/povbutton.py
commands2/button/trigger.py
commands2/sysid/__init__.py
commands2/sysid/sysidroutine.py
robotpy_commands_v2-2025.3.2.dist-info/LICENSE
robotpy_commands_v2-2025.3.2.dist-info/METADATA
robotpy_commands_v2-2025.3.2.dist-info/WHEEL
robotpy_commands_v2-2025.3.2.dist-info/top_level.txt
robotpy_commands_v2-2025.3.2.dist-info/RECORD
