Metadata-Version: 2.2
Name: robotpy-commands-v2
Version: 2025.3.2
Summary: WPILib command framework v2
Home-page: https://github.com/robotpy/robotpy-commands-v2
Author: RobotPy Development Team
Author-email: robotpy@googlegroups.com
License: BSD-3-Clause
Requires-Python: >=3.9
License-File: LICENSE
Requires-Dist: wpilib<2026,>=2025.1.1
Requires-Dist: typing_extensions<5,>=4.1.0
Dynamic: author
Dynamic: author-email
Dynamic: home-page
Dynamic: license
Dynamic: requires-dist
Dynamic: requires-python
Dynamic: summary
